convert_poetry2uv.py
convert_poetry2uv-0.3.11.dist-info/METADATA
convert_poetry2uv-0.3.11.dist-info/WHEEL
convert_poetry2uv-0.3.11.dist-info/entry_points.txt
convert_poetry2uv-0.3.11.dist-info/top_level.txt
convert_poetry2uv-0.3.11.dist-info/RECORD
