Metadata-Version: 2.4
Name: convert-poetry2uv
Version: 0.3.11
Summary: Poetry to uv tool. To migrate from a poetry managed repo to uv.
Author-email: Bart <bart@bamweb.nl>
Project-URL: Pull Requests, https://github.com/bartdorlandt/convert_poetry2uv/pulls
Project-URL: Bug Tracker, https://github.com/bartdorlandt/convert_poetry2uv/issues
Project-URL: Changelog, https://github.com/bartdorlandt/convert_poetry2uv/blob/main/CHANGELOG.md
Project-URL: Repository, https://github.com/bartdorlandt/convert_poetry2uv
Requires-Python: >=3.10
Requires-Dist: tomlkit>=0.13.2
